npc_maker/__init__.py
npc_maker/ctrl.py
npc_maker/env.py
npc_maker/evo.py
npc_maker-0.2.0.dist-info/METADATA
npc_maker-0.2.0.dist-info/WHEEL
npc_maker-0.2.0.dist-info/top_level.txt
npc_maker-0.2.0.dist-info/RECORD
