Metadata-Version: 2.4
Name: npc-maker
Version: 0.2.0
Summary: Evolve AIs in simulated environments
Author-email: David McDougall <dam1784@rit.edu>
License-Expression: MIT-0
Project-URL: Repository, https://github.com/ctrl-z-9000-times/npc_maker
Classifier: Natural Language :: English
Classifier: Operating System :: OS Independent
Classifier: Programming Language :: Python :: 3
Classifier: Intended Audience :: Science/Research
Classifier: Topic :: Scientific/Engineering :: Artificial Life
Requires-Python: >=3.12
